{
  "generated_at": "2026-03-05T08:32:47.288296+09:00",
  "advice": "おはようございます。清々しい快晴の木曜日ですね。\n\n現在の体感温度は6.9°C。雲一つない空から地表の熱が宇宙空間へと逃げていく「放射冷却」が進み、キリッと冷えた朝を迎えました。さらに、わずかな風が肌から熱を奪う「風冷効果」により、実際の気温以上に寒く感じられます。\n\n今日は二十四節気の「啓蟄（けいちつ）」。土の中で眠っていた虫たちが春の訪れを感じて動き出す頃です。まさに三寒四温の真っ只中で、昨日の穏やかな暖かさと比べると、今朝の空気は少し厳しく感じるかもしれません。日中は日差しの温もりを期待できますが、夜23時頃には5.5°C、明朝には3°C台まで再び下がる予報です。お帰りが遅くなる方は、厚手のコートやストールを忘れずに。\n\n空気も43.0%と乾燥しています。出がけに温かい飲み物で喉を潤し、体を内側から温めてあげてくださいね。週の後半で少し疲れが出る頃ですが、視程24kmという澄み渡った青空が、きっとあなたの背中を優しく押してくれますよ。\n\nお気をつけて、いってらっしゃいませ！😊🌸🧥\n\n次回更新は9:00頃です。",
  "data_summary": {
    "outdoor_temp": 8.5,
    "weather_temp": 6.6,
    "weather": "快晴",
    "alerts_count": 0
  }
}