{
  "generated_at": "2026-03-27T13:34:07.015446+09:00",
  "advice": "現在は13時を過ぎ、一日の中で最も気温が上がる時間帯ですね。現在の体感温度は15.9°C。ここ2日間は最高気温が14°Cを下回る「花冷え」のような寒さが続いていましたが、今日はようやく春本来のポカポカとした陽気が戻ってきました。🌸\n\n太陽からのエネルギーが地面を直接温める「日射」の影響が強く、UV指数も5.35と、この時期としてはやや高めの数値です。お昼休みに少し外を歩くだけでも、心地よい刺激になりますよ。ただし、風が肌に触れて熱を奪う「風冷効果」により、日陰に入ると数字以上にヒンヤリと感じるかもしれません。長袖シャツに薄手の羽織ものを一枚重ねるくらいが、今の外歩きにはちょうど良いスタイルです。\n\n今日は金曜日、一週間の締めくくりですね。今夜は「上弦の月」が空を彩ります。夕方以降は、太陽が沈み地表の熱が空へと逃げていく「放射冷却」が進むため、再び冷え込みが強まります。夜までお出かけの方は、ストールなどで首元を保護して体温を逃さないようにしてください。あと数時間、軽やかな足取りで頑張りましょう。応援しています！✨\n\n次回更新は14:00頃です。",
  "data_summary": {
    "outdoor_temp": 16.8,
    "weather_temp": 14.7,
    "weather": "晴れ",
    "alerts_count": 0
  }
}