{
  "generated_at": "2026-04-23T16:19:06.668002+09:00",
  "advice": "現在の体感温度は16.1°C。しっとりとした雨が降っていますが、この雨もあと1時間ほどで止む見込みです。\n\n今日は二十四節気の「穀雨」。田畑を潤す恵みの雨の季節ですが、昨日までの初夏のような陽気から一転、最高気温は19.3°Cに留まりました。昨日に比べて4度以上も低いため、体感的には「花冷え」のような肌寒さを感じるかもしれませんね。 🌧️\n\n現在は分厚い「層雲（どんよりと広がる低い雲）」が空を覆い、太陽のエネルギーを遮っています。一方で、高い湿度が地表の熱を逃がさない「逆放射」の効果を生んでいるため、夜にかけての極端な冷え込みはなさそうです。\n\n予報では17時過ぎには雨が上がり、お帰りの時間帯には傘を畳んで歩けそうですよ。夜には雲の切れ間から、輝面率38％ほどの「上弦の月」が優しく顔をのぞかせるかもしれません。🌓\n\n週の後半、疲れが溜まりやすい木曜日ですね。冷たい雨で少し冷えた帰宅後は、ゆっくりお風呂に浸かって、湿気で重くなった体をリセットしてあげてください。温かい夕食が、今日一日の頑張りを癒してくれますよ。 😊✨\n\n次回更新は17:00頃です。🧥🌸",
  "data_summary": {
    "outdoor_temp": 15.9,
    "weather_temp": 14.5,
    "weather": "霧雨",
    "alerts_count": 0
  }
}