{
  "generated_at": "2026-02-06T21:45:44.653909+09:00",
  "advice": "現在の体感温度は7.7°C。今日は日中に14.5°Cまで上がり、この一週間で最も暖かい一日となりました。しかし、今朝の最低気温0.0°Cとの差は14度以上。一日の気温差である「日較差（にちこうさ）」がこれほど大きいと、自律神経に負担がかかる寒暖差疲労を感じやすくなります。金曜日の夜、一週間の疲れも相まって少し体が重く感じてはいませんか？ ☕️✨\n\n今夜は薄曇りの空模様ですね。雲がない夜は、地表の熱が宇宙へ逃げていく「放射冷却」によって急激に冷え込みますが、今夜は雲が大気の熱を地面へ送り返す「逆放射」という現象が起きるため、氷点下のような極端な冷え込みは避けられそうです。それでも空気は乾燥しており、体感ではしっかりとした寒さを感じます。\n\nちょうど今、東の空から「十八夜月」が昇ってきました🌖。輝面率77%の少し欠けた月が、お仕事を終えたあなたを優しく見守っているようです。今夜は少し長めに湯船に浸かり、頑張った体を労わってあげてくださいね。お布団に入る際は、首元を冷やさないよう工夫すると、深い眠りにつけますよ。\n\n一週間、本当にお疲れ様でした。温かくして、リラックスした夜をお過ごしください。☺️🧣\n\n次回更新は22:00頃です。",
  "data_summary": {
    "outdoor_temp": 8.5,
    "weather_temp": 6.4,
    "weather": "薄曇り",
    "alerts_count": 0
  }
}