{
  "generated_at": "2026-07-24T17:03:05.735634+09:00",
  "advice": "金曜日の帰宅時間帯、外は現在44.5 mm/hという非常に激しい雨が降っています。視界が急速に悪化していますので、お帰りの際は足元や車の運転に十分ご注意ください。☔\n\n現在の気温は27.7°Cですが、肌で感じる体感温度は32.1°Cと体に熱がまとわりつくような暑さです。これは、湿度89.0%という極めて湿った大気が、汗の蒸発による体温調節を妨げる「不快指数」を高めているためです。さらに、厚い雨雲から熱が地表へ送り返される「逆放射」の働きにより、気温が下がりにくくなっています。🥵\n\n幸いにも、30分後には7.75 mm/h程度まで雨が弱まる予報です。今すぐ帰路につくよりも、少し雨宿りをしてピークをやり過ごしてから動き出すのがスマートですよ。大暑の厳しい湿気で体力が削られやすいので、帰宅後もエアコンを適切に使って、一週間の疲れをゆったりと癒やしてくださいね。✨\n\n次回更新は18:00頃です。",
  "data_summary": {
    "outdoor_temp": 27.7,
    "weather_temp": 27.5,
    "weather": "雨",
    "alerts_count": 0
  }
}