{
  "generated_at": "2026-06-16T08:46:34.889014+09:00",
  "advice": "現在の体感温度は22.9°Cと、非常に過ごしやすい朝を迎えています。ただ、足元ではポツポツとごく弱い雨が観測されていますね。🌧️\n\nこの雨は一時的なもので、日中は薄曇りから晴れへと天気が回復していく見込みです。今朝少しひんやりと感じられたのは、雲の隙間から地表の熱が宇宙へと逃げていく「放射冷却」が緩やかに働いたため。最低気温は16.7°Cまで下がり、ここ数日の中でも涼しく心地よい朝となりました。\n\n今日は火曜日、お仕事や学校へと向かう時間帯ですね。お出かけの瞬間は、念のため折りたたみ傘があると安心ですが、日中には必要がなくなりそうです。過ごしやすい一日になりますが、朝晩との寒暖差に備えて、半袖の上にサッと羽織れる薄手の上着があると重宝しますよ。\n\n今日は月が太陽と重なり姿を隠す「新月」です。物事をリセットし、新しく始めるのに最適なタイミング。深呼吸をして、心軽やかに一歩を踏み出していきましょう。😊✨\n\n次回更新は9:00頃です。",
  "data_summary": {
    "outdoor_temp": 22.8,
    "weather_temp": 21.5,
    "weather": "薄曇り",
    "alerts_count": 0
  }
}