{
  "generated_at": "2026-05-26T16:35:58.364565+09:00",
  "advice": "現在、手元のセンサーでは体感温度27.8°Cを観測しています。実際の気温26.6°Cよりも高く、少し動くとじんわりと汗ばむような暑さですね。これは湿度59.0%という空気中の豊かな水分が肌からの汗の蒸発を妨げ、体に熱が残りやすくなる「潜熱」の作用によるものです。お部屋の空気を通したり、水分をこまめに摂ったりして心地よくお過ごしください。☀️\n\nまもなく18時46分に日の入りを迎えると、今度は地表の熱が宇宙へと逃げていく「放射冷却」が始まり、空気は急速にひんやりとしてきます。火曜日の夕方から夜にかけてお仕事帰りや買い出しで外出される際は、日中の暑さに惑わされず、カバンに薄手のカーディガンなどを忍ばせておくと安心ですよ。🧥\n\n現在は万物の生命が次第に満ちていくとされる二十四節気「小満」の真っ只中。今夜は満月へと満ちていく途中の美しい「十三夜月」が夜空を優しく照らします。一日の終わりに美しい月を眺めながら、深呼吸をして心身を整えてみてくださいね。✨\n\n次回更新は17:00頃です。",
  "data_summary": {
    "outdoor_temp": 26.6,
    "weather_temp": 25.6,
    "weather": "薄曇り",
    "alerts_count": 0
  }
}