{
  "generated_at": "2026-06-24T17:49:07.950927+09:00",
  "advice": "今日もお疲れ様です！週の折り返しの水曜日、帰路につく頃でしょうか。😊\n\n現在の体感温度は25.9°Cと、実際の気温24.1°Cよりも高くなっています。これは湿度が72%と高いため、汗が蒸発して体温を奪う「潜熱」による冷却効果が十分に働かず、体に熱がこもりやすくなっているからです。風が穏やかなこともあり、少しじっとりとした蒸し暑さを感じやすいでしょう。お帰りの際は、風通しの良い服装がおすすめですよ。\n\n日中は27.0°Cまで気温が上がり、体に少し疲れが溜まる暑さでしたね。帰宅途中も油断せず、喉が渇く前にこまめな水分補給を心がけてください。\n\n今夜は空一面を雲が覆っていますが、雲の向こうには「上弦の月」が隠れています。タイミングが良ければ、雲の隙間から少し満ちてきた月が顔を出してくれるかもしれません。おうちに帰ったら、エアコンの除湿機能などを上手に使って、さらりと快適にしてからゆっくり心と体を休めてくださいね。✨\n\n次回更新は18:00頃です。",
  "data_summary": {
    "outdoor_temp": 24.1,
    "weather_temp": 23.5,
    "weather": "曇り",
    "alerts_count": 0
  }
}