{
  "generated_at": "2026-07-11T20:57:02.524666+09:00",
  "advice": "土曜日の夜、いかがお過ごしでしょうか。現在の外気温は27.0°Cですが、湿度が79.0%と非常に高いため、私たちの肌が感じる体感温度は30.5°Cと、かなり蒸し暑い夜になっています。🥵\n\nこれほど蒸し暑く感じるのは、水分が気体に変わる時に周囲の熱を奪い去る「潜熱」の働きが、空気中の豊かな水蒸気によって妨げられ、体温を逃がすための汗が乾きにくくなっているためです。\n\n今夜は、エアコンの除湿機能や冷房を上手に活用して、室内の湿度を下げるのが快適に眠るコツです。設定温度は27〜28°Cと高めでも、湿度が下がるだけで体感温度はグッと下がりますよ。冷えすぎを防ぐために、お腹を冷やさない寝具を用意してお休みくださいね。布団に入る前のコップ1杯の水分補給もお忘れなく。💧\n\n深夜0時41分頃には、東の空から細い二十六夜月が静かに昇ってきます。少し夜更かしをされる方は、涼しい部屋の窓辺から、昇りゆく月を探してみてはいかがでしょうか。穏やかな週末の夜をお過ごしくださいね。✨\n\n次回更新は21:00頃です。",
  "data_summary": {
    "outdoor_temp": 27.0,
    "weather_temp": 25.0,
    "weather": "晴れ",
    "alerts_count": 0
  }
}