{
  "generated_at": "2026-05-16T07:55:45.066596+09:00",
  "advice": "土曜日の朝、いかがお過ごしでしょうか。現在の体感温度は19.3°C。空気中の水蒸気が熱を保持する「温室効果」に加え、大気が熱を地面へ送り返す「逆放射」により、冷え込みが抑えられたしっとりとした朝を迎えています。😊\n\n昨日の最高気温は23.9°Cまで上がりましたが、今朝の実測値を見ると、今日は少し落ち着いた気温推移になりそうです。湿度が76.0%と高めなのは、空気が冷えて水蒸気が飽和に近づく「露点温度」との差が小さいため。この湿り気が、日中の急激な温度上昇を和らげるクッションの役割を果たしてくれます。二十四節気では「立夏」を過ぎ、暦の上では夏ですが、今日は「三寒四温」の余韻を感じるような、過ごしやすい春の涼しさとなるでしょう。🌸\n\nお出かけには長袖シャツに、脱ぎ着しやすい羽織ものを一枚持っておくと、時間帯ごとの変化にも柔軟に対応できます。また、今は「二十六夜月（にじゅうろくやづき）」と呼ばれる非常に細い月が、日の出前の空を静かに飾っていました。新月に向けて月が欠けていくこの時期は、心身のデトックスや整理整頓にも向いています。✨\n\n一週間頑張った自分を労りつつ、穏やかな週末をお過ごしくださいね。\n\n次回更新は8:00頃です。",
  "data_summary": {
    "outdoor_temp": 19.0,
    "weather_temp": 14.5,
    "weather": "薄曇り",
    "alerts_count": 0
  }
}