{
  "generated_at": "2026-05-09T19:56:27.212949+09:00",
  "advice": "現在の体感温度は18.0℃。日中は実測で23.3℃まで上がり、初夏を思わせる陽気でしたが、日没とともに少しずつ空気が涼しく感じられるようになってきました。\n\n今夜は雲が少なく、湿度が32.0%と非常に低いのが特徴です。そのため、地表の熱が遮るものなく宇宙空間へと逃げていく「放射冷却」という現象がこのあと本格的に強まります。深夜から明朝にかけては、今日記録した最低気温17.3℃をさらに下回り、数字以上に肌寒く感じるかもしれません。\n\n今日は土曜日ですので、夜更かしを楽しまれる方も多いかと思います。ただ、空気の乾燥が喉に負担をかけやすい状況です。眠る前には加湿を意識したり、枕元に一枚多めの羽織ものを用意したりして、お体をいたわってくださいね。\n\nまた、日付が変わる頃には東南東の空から、輝面率60%ほどの「下弦の月」が昇ってきます。空気が澄んでいるため、深夜の静寂の中で美しい月光を楽しめるはずですよ。寒暖差で体調を崩さないよう注意して、素敵な週末の夜をお過ごしください。🌙🌸\n\n次回更新は20:00頃です。",
  "data_summary": {
    "outdoor_temp": 19.2,
    "weather_temp": 16.9,
    "weather": "晴れ",
    "alerts_count": 0
  }
}