{
  "generated_at": "2026-04-10T19:53:23.338834+09:00",
  "advice": "雨は今がちょうど止み際ですね。19時20分頃にはしっかりとした雨が降っていましたが、現在は0.85mmと弱まり、あと30分もすれば落ち着く見込みです。お帰りの際、電車やお店に傘を置き忘れないようお気をつけください。🌧️\n\n現在の外気温は19.4℃ですが、湿度が95％と非常に高く、体感温度は21.0℃と少し暖かく感じられます。空気中の水蒸気が多いため、汗が蒸発して肌から熱を奪う「潜熱」の働きが鈍くなり、春の夜らしい、湿り気を帯びた柔らかな空気に包まれています。🌡️\n\nただ、気圧が1000hPaを切る低気圧の領域にいるため、血管が拡張しやすく、頭痛やだるさを感じている方も多いかもしれません。一週間の疲れが溜まる金曜日、こうした気圧の変化は体にこたえますよね。今夜は無理をして動かず、ぬるめのお湯に浸かって心身をゆるめてあげてください。✨\n\n日付が変わる1時頃には、欠けていく「下弦の月」が南東から静かに昇ってきます。雨上がりのしっとりとした夜、明日からの週末に向けて、まずは自分自身をたっぷり労わってあげましょう。☺️\n\n次回更新は20:00頃です。",
  "data_summary": {
    "outdoor_temp": 19.4,
    "weather_temp": 18.9,
    "weather": "曇り",
    "alerts_count": 2
  }
}