{
  "generated_at": "2026-05-16T08:56:31.566522+09:00",
  "advice": "土曜日の朝、清々しい空気ですね。現在の体感温度は20.4°Cと、長袖シャツ一枚で心地よく過ごせる「完璧な春の朝」を迎えています。今週は28°Cを超える夏日のような暑さもありましたが、今日は一転して落ち着いた、体に優しい陽気です。😊\n\n現在は1020hPaを超える勢力の強い高気圧に覆われています。高気圧の圏内では、上空から空気が降りてくる「下降気流」が起きるため、雲が消えやすく、今日のような澄んだ青空が広がります。絶好の洗濯・行楽日和となりますが、一点だけご注意を。雲が太陽光を遮る「アルベド（反射率）」の影響が少ない快晴日は、肌への刺激がダイレクトに届きます。現在のUV指数は4.55ですが、正午前後にはさらに強まりますので、日傘や帽子で賢く対策しましょう。☀️🧥\n\nまた、大気中の水蒸気が地表の熱を適度に保つ「逆放射」の効果により、今夜から明朝にかけての冷え込みも穏やかな見込みです。明日の新月を前に、今朝は「二十六夜月」と呼ばれる細い月が、日の出前の東の空を密かに彩っていました。心のリフレッシュに最適な、穏やかな週末になりそうですね。✨\n\n今日という日が、あなたにとって実り多き一日となりますように。\n次回更新は9:00頃です。",
  "data_summary": {
    "outdoor_temp": 20.1,
    "weather_temp": 17.3,
    "weather": "晴れ",
    "alerts_count": 0
  }
}