{
  "generated_at": "2026-04-18T12:42:53.695159+09:00",
  "advice": "春の陽気が心地よい土曜日の昼下がりですね。現在の体感温度は20.2°Cと、長袖シャツ一枚で過ごすのに最適な「清明（せいめい）」らしい清々しさです。🌸\n\n注目すべきは、太陽の角度が高くなり、地表に届く紫外線のエネルギーが強まる「UV指数」が6.75に達している点です。短時間の外出でも日焼けしやすいため、日傘や帽子での対策を万全に。ただし、突風にはご注意ください。瞬間的に秒速10メートル近い風が吹くタイミングがあり、お気に入りの帽子が飛ばされやすい状況です。👒\n\nまた、今は空気が比較的乾燥しているため、水分が蒸発する際に周囲から熱を奪う「潜熱（せんねつ）」の働きにより、日陰に入ると数字以上に涼しく感じられるはずです。この湿度の低さは、夜間に地表の熱が宇宙へと逃げていく「放射冷却」を強め、日没後の急な冷え込みを招きます。夕方以降もお出かけになるなら、薄手のジャケットやカーディガンを一枚持っておくと安心ですよ。✨\n\n新月を過ぎたばかりの今夜は、月明かりに邪魔されず夜空の星が主役になる時間です。心豊かな週末をお過ごしください。😊\n\n次回更新は13:00頃です。",
  "data_summary": {
    "outdoor_temp": null,
    "weather_temp": 20.4,
    "weather": "晴れ",
    "alerts_count": 0
  }
}