{
  "generated_at": "2026-07-08T18:20:54.004142+09:00",
  "advice": "お疲れ様です。週の折り返しとなる水曜日の夕方、いかがお過ごしですか？⛅\n\n二十四節気の「小暑」を迎え、暑さが本格化してきました。今日の最高気温は31.1℃に達し、ここ1週間で最も暑い1日に。昨日の涼しさから一転して急激に気温が上がったため、お体に堪えているのではないでしょうか。\n\n日没を控えた現在も、体感温度は29.3℃と厳しい蒸し暑さが続いています。🌡️\nこれは、汗が蒸発する際に体から熱を奪う「潜熱」の働きが、68％という高い湿度のせいで遮られ、体に熱がこもりやすくなっているためです。\n\nまだ体が暑さに慣れていない時期ですので、帰宅後はエアコンの除湿機能を上手に使い、室内の環境を快適に整えてくださいね。冷たい麦茶などで水分を補給し、ゆっくり休んで自律神経を整えましょう。💧\n\n今夜遅くには下弦の月が昇ります。今日1日頑張ったご自身をたっぷり労り、今夜は心地よいお部屋でどうぞごゆっくりお休みください。☺️\n\n次回更新は19:00頃です。",
  "data_summary": {
    "outdoor_temp": 27.4,
    "weather_temp": 25.6,
    "weather": "晴れ",
    "alerts_count": 0
  }
}