{
  "generated_at": "2026-02-06T10:56:46.395538+09:00",
  "advice": "日差しが背中を温めてくれる、心地よい午前中ですね。現在の体感温度は10.2°C。風がほとんどないため、数字以上に温かみを感じるはずです。今朝は1.5°Cまで冷え込みましたが、これは雲がない快晴の夜に、地表の熱が宇宙へ逃げていく「放射冷却」が強まったためです。\n\n午後にかけてもこの安定した晴天が続き、日中の活動を応援してくれそうです。ただ、空気の湿度が45.0%と低くなっています。お肌の保湿はもちろん、大気が乾燥すると喉の粘膜のバリア機能が低下しやすいため、室内では加湿器を活用して喉を労わってあげてくださいね。\n\n昨日の最高気温12.9°Cと比較すると、今日はわずかに落ち着いた気温推移となっていますが、立春を過ぎた「光の春」を感じさせる力強い光が届いています。金曜日で少しお疲れの時間帯かもしれませんが、少し外の空気を吸って、遠くの景色を眺めてみませんか。視程が24kmと良好なので、遠くの建物や山の稜線がくっきりと見え、リフレッシュに最適ですよ。\n\n今夜は月齢18.5の「十八夜月」が夜空を飾ります。帰宅時は冷え込みますが、澄んだ冬の空に浮かぶ月を眺めて、一週間頑張った自分を癒やしてあげてください。☀️🧥✨\n\n次回更新は11:00頃です。",
  "data_summary": {
    "outdoor_temp": 10.3,
    "weather_temp": 8.6,
    "weather": "快晴",
    "alerts_count": 0
  }
}