{
  "generated_at": "2026-03-26T07:38:23.365854+09:00",
  "advice": "木曜日の朝、外はしとしとと冷たい雨が降り続いていますね。現在、1時間に2.4mmほどの雨が1時間以上継続しており、この先もしばらくは雨具が手放せない状況です。\n\n特筆すべきは93%という極めて高い湿度です。空気が含める水蒸気の限界に近い「飽和」の状態にあるため、微細な水滴が視界を遮る「もや」が発生し、景色が少し白く霞んでいます。現在の体感温度は10.8°C。数日前は17°Cを超える春の陽気でしたが、今日は季節が逆戻りしたような肌寒さです。これは、暖かい空気の下に冷たい空気が潜り込むことで大気が安定し、低い雲が広がり続ける「層雲」が卓越しているためと考えられます。\n\n今日は空中の水分が服に付着しやすいため、撥水性のある上着を選ぶのが正解です。週の後半、雨の中の通勤は少し億劫かもしれませんが、この雨は植物の成長を促す「催花雨（さいかう）」という美しい別名もあります。足元に十分気をつけて、温かい飲み物で心にゆとりを持って出発しましょう。今日一日があなたにとって素敵なものになりますように。😊☔🧥\n\n次回更新は8:00頃です。",
  "data_summary": {
    "outdoor_temp": 10.9,
    "weather_temp": 9.1,
    "weather": "強い霧雨",
    "alerts_count": 0
  }
}