{
  "generated_at": "2026-02-11T15:08:28.909090+09:00",
  "advice": "現在は体感温度6.8°Cと、冬らしい寒さが続いています。今日は建国記念の日ですね。朝の雨でたっぷりと湿気を含んだ空気が、肌を刺すような冷たさを和らげている一方で、独特のしっとりとした重みを感じる午後となっています。🧥\n\n気象学的に見ると、今の空気は湿度が高いため、乾燥した日よりも熱を蓄えやすい性質を持っています。しかし、太陽が西へ傾くにつれて空気は急速に冷えていきます。これからの時間帯、上空の雲が地表の熱を逃がさない蓋のような役割を果たす「逆放射」が働きますが、それでも日没の17時17分を過ぎれば気温は着実に低下します。\n\n祝日の午後をいかがお過ごしでしょうか。夕方からお出かけになるなら、湿り気を帯びた冷気から身を守るために、マフラーなどで首元をしっかりガードしてくださいね。室内では湿度が十分にあるため喉への負担は少なそうですが、お風呂場など温度差のある場所での「ヒートショック」には十分な警戒が必要です。☁️\n\n深夜には、月齢23の「下弦の月」が東の空に昇ります。立春を過ぎ、暦の上では春へと向かう静かな変化を、冷たく澄んだ夜空に探してみるのも素敵ですよ。🌗✨\n\n次回更新は16:00頃です。",
  "data_summary": {
    "outdoor_temp": 6.5,
    "weather_temp": 5.9,
    "weather": "薄曇り",
    "alerts_count": 0
  }
}