{
  "generated_at": "2026-01-16T17:36:18.724106+09:00",
  "advice": "現在の体感温度は10.9°C。日中は16°Cを超えて冬としては過ごしやすかった分、日没後の急な冷え込みが体に堪えますね。金曜日、一週間本当にお疲れ様でした！😊\n\n今夜は雲一つない快晴です。そのため、地表の熱が宇宙空間へどんどん逃げていく「放射冷却」がこれから本格的に進みます。深夜から明朝にかけては、今朝の最低気温3.3°Cをさらに下回る厳しい冷え込みになるでしょう。また、湿度が34.0%と非常に低くなっています。空気が乾燥すると、喉の粘膜の防御機能が下がったり、火災のリスクも高まったりするため、加湿器の活用や火の元への注意が欠かせません。🧣\n\nこれから帰宅される方は、マフラーや手袋で「風冷効果」から身を守り、暖かくして歩いてくださいね。お家では温かい湯船に浸かってリラックスするのが一番ですが、急激な温度変化で血圧が変動する「ヒートショック」を防ぐため、脱衣所もしっかり暖めておきましょう。🛀\n\n今夜は月齢27.3の細い月が深夜に昇るまで、澄んだ空に満天の星が広がります。週末を前に、ふと空を見上げて心ほぐれるひとときをお過ごしください。✨\n\n次回更新は18:00頃です。",
  "data_summary": {
    "outdoor_temp": 12.8,
    "weather_temp": 10.6,
    "weather": "快晴",
    "alerts_count": 0
  }
}