{
  "generated_at": "2026-01-08T13:31:44.356727+09:00",
  "advice": "現在の体感温度は7.4°C。快晴の空から明るい光が降り注いでいますが、北西からの風が体温を奪う「風冷効果」により、肌感覚では一桁台の厳しい寒さが続いています。🧣\n\n今朝は氷点下0.9°Cまで下がり、記録開始以来の最低気温に迫る冷え込みとなりました。これは雲ひとつない空から地表の熱が宇宙空間へ逃げていく「放射冷却」が強烈に起きたためです。さらに湿度が39.0%と非常に低く、空気が乾燥していることも気温の急降下を後押ししました。\n\n午後は日差しの温もりを感じられる貴重な時間ですが、湿度が低いためウイルスが活性化しやすく、喉の乾燥にも注意が必要です。木曜日の午後、少し疲れが見える時間帯ですので、温かい飲み物で水分補給をしてホッと一息ついてくださいね。\n\n日が暮れる16時43分を過ぎると、再び気温が急降下します。お帰りが夜になる場合は、しっかりとした防寒対策が欠かせません。今夜は澄んだ空に「十八夜月」が美しく昇ります。冷え込む夜空を見上げながら、温かくして過ごしましょう。💪✨\n\n次回更新は14:00頃です。",
  "data_summary": {
    "outdoor_temp": 9.6,
    "weather_temp": 9.4,
    "weather": "快晴",
    "alerts_count": 0
  }
}