{
  "generated_at": "2026-06-21T17:57:44.189453+09:00",
  "advice": "一年で最も昼が長い夏至の夕方、間もなく日没を迎えますが、まだ空にはうっすらと明るさが残っていますね。日曜日の穏やかな夕暮れ時、いかがお過ごしでしょうか。✨\n\n現在の気温は26.6°Cですが、湿度が80%と非常に高いため、肌にまとわりつくような28.1°Cの蒸し暑さを感じます。これは、汗など水分が蒸発する際に周囲の熱を奪う「気化熱」の働きが、空気中の豊かな水蒸気によって妨げられているためです。体に熱がこもりやすい気象条件ですので、室内でも喉が渇く前にしっかりと水分を摂ってくださいね。💧\n\n今夜は雲が広がることで、地表の熱が宇宙へ逃げていく「放射冷却」が起こりにくく、夜間も気温が下がりにくい予想です。少し寝苦しい夜になりそうですので、エアコンの除湿機能を上手に使って、寝具や室温を快適に整えましょう。夜遅くには上弦の月が西の空へと傾いていきます。週明けに向けて、心穏やかでリラックスした夜をお過ごしください。☺️\n\n次回更新は18:00頃です。",
  "data_summary": {
    "outdoor_temp": 26.6,
    "weather_temp": 26.2,
    "weather": "薄曇り",
    "alerts_count": 0
  }
}