{
  "generated_at": "2026-04-01T20:56:33.768010+09:00",
  "advice": "現在の体感温度は11.1°C。しっとりとした雨が降り続いています。湿度が95%と非常に高く、気温と、空気中の水蒸気が冷やされて水滴に変わり始める「露点温度」が10.4°Cと非常に近いため、辺りにはもやが立ち込めていますね。🌧️\n\n週の折り返しとなる水曜日の夜、いかがお過ごしでしょうか。この後30分ほどで雨が一時的に強まる予報が出ています。外出の予定がなければ、雨音をBGMに早めに心身を休めるのがよさそうです。本来なら今夜は輝面率99%を超えるほぼ満月ですが、厚い雲が大気の熱を地面へ送り返す「逆放射」の役割を果たすため、晴れた夜のような放射冷却による急激な冷え込みは抑えられそうです。\n\n明後日には万物が清らかに生き生きとする二十四節気の「清明」を迎えます。今の雨はまさに、春の芽吹きを促す「催花雨（さいかう）」と言えるでしょう。🌸\n\nおやすみ前には温かい飲み物で一息ついて、リラックスしてくださいね。明日の朝も11°C前後の肌寒さが残る見込みですので、枕元に羽織るものを用意しておくと、スムーズに一日を始められますよ。😊✨\n\n次回更新は21:00頃です。",
  "data_summary": {
    "outdoor_temp": 11.2,
    "weather_temp": 11.1,
    "weather": "強い霧雨",
    "alerts_count": 0
  }
}