{
  "generated_at": "2026-02-24T23:05:13.318757+09:00",
  "advice": "現在の体感温度は11.2°C。風が穏やかなため、肌を刺すような寒さではありませんが、昨日の20°Cを超える春のような陽気から一転し、一気に冬の冷たい空気に包まれていますね。この数日の激しい寒暖差は「寒冷ストレス」として体に蓄積されやすいため、今夜は特に意識的な休息が必要です。\n\n今夜は空に60%以上の雲が広がっています。晴れた夜のように地表の熱が宇宙へ逃げていく「放射冷却」は、雲が蓋の役割を果たすことで遮られています。さらに、大気が地表に向けて熱を放射する「逆放射」の効果もあり、明日の朝にかけての冷え込みは、氷点下を記録した数日前に比べれば緩やかになる見込みです。\n\nとはいえ、明朝も10°Cを下回る気温が予想されます。お休み前には、湯船で深部体温を上げ、寝室の湿度を保つ工夫をしましょう。空気が冷えて水蒸気が飽和しやすくなる「露点温度」は現在7.8°C。窓際での結露も起きやすい状態ですので、カーテンをしっかり閉めて冷気を遮断してください。\n\n夜空には「上弦の月」が輝き、深夜1時過ぎに西北西の空へと沈んでいきます。週の中日に向けて、心身を温かくして英気を養ってくださいね。\n\n次回更新は1:00頃です。",
  "data_summary": {
    "outdoor_temp": 11.4,
    "weather_temp": 9.3,
    "weather": "薄曇り",
    "alerts_count": 0
  }
}