{
  "generated_at": "2026-02-26T04:49:50.489015+09:00",
  "advice": "現在の体感温度は4.2°C。吐く息が真っ白に染まる、真冬の寒さが戻った木曜の早朝ですね。\n今朝は分厚い雲が空を覆っています。地表の熱が宇宙へ逃げていく「放射冷却」は抑えられているものの、太陽の光が遮られるため、日中も気温はあまり上がらない見込みです。\n\nここ数日の変化を振り返ると、20°Cを超えた数日前から一気に15°C近くも気温が急降下しています。このように短期間で気温が激しく上下すると、体温を調節する自律神経に大きな負担がかかる「寒暖差疲労」が起こりやすくなります。週の後半で疲れも溜まりやすい時期ですので、今日は決して無理をせず、意識的にご自身を労わってあげてくださいね。🧥✨\n\n外出の際は、風を通さない厚手のコートにマフラーを重ねるのが正解です。湿度が88%と高いため喉には優しい朝ですが、水分を含んだ冷気が肌にまとわりつくような重い寒さを感じます。温かいスープや飲み物で内側からしっかり熱を作り、心に余裕を持って一日をスタートしましょう。応援しています。💪☺️\n\n次回更新は7:00頃です。",
  "data_summary": {
    "outdoor_temp": 5.6,
    "weather_temp": 5.2,
    "weather": "曇り",
    "alerts_count": 0
  }
}