{
  "generated_at": "2026-03-25T19:00:56.188463+09:00",
  "advice": "雨の降る水曜日の夜、お疲れ様です。現在の体感温度は11.6°C。数字以上にひんやりと感じられるのは、湿度が90.0%と非常に高いためですね。☔\n\n実測データを確認すると、18時台の強い降りからピークを過ぎ、雨脚は現在1.25mm/hまで弱まってきました。1時間後にはさらに落ち着く予報ですので、慌てて帰路につく必要はなさそうです。今日は、空気が冷えて水蒸気が飽和する「露点温度」と、実際の気温が非常に近くなっています。その影響で、どんよりとした低い雲である「層雲」が広がり、視界の悪い霧雨をもたらしています。視程が落ちやすいため、車の運転や足元には十分にお気をつけください。\n\n今日は今週で最も最高気温が低い一日となりました。まさに桜の開花を足踏みさせる「花冷え」ですね。🌸\n週の折り返し、帰宅後は水蒸気が水へと変わる際に放出される熱「潜熱」を活かした温かいお風呂で、じっくりと体を温めてください。あいにくの天気ですが、雲の向こう側では輝面率41.1%の「上弦の月」が静かに満ちていく途中にあります。明日は今日よりも少し過ごしやすくなりますよ。☺️✨\n\n次回更新は20:00頃です。",
  "data_summary": {
    "outdoor_temp": 11.9,
    "weather_temp": 10.5,
    "weather": "霧雨",
    "alerts_count": 0
  }
}