{
  "generated_at": "2026-07-04T09:05:39.254314+09:00",
  "advice": "穏やかな土曜日の朝ですね。現在の体感温度は24.8°Cですが、湿度が80.0%と非常に高いため、数値以上にじっとりとした蒸し暑さを感じやすい状況です。⛅\n\nこのように空気中の水分が多いと、かいた汗が肌の上で蒸発しにくくなります。水分が気体に変わる際に周囲から熱を奪う「潜熱」の放出が妨げられるため、体に熱がこもりやすく、熱中症のリスクが上がりやすくなります。今日はお出かけや家事の合間に、エアコンの除湿機能を上手に使って快適な環境を整えましょう。💧\n\nカレンダーに目を向けると、あと2日で本格的な暑さの始まりを告げる「小暑」を迎えます。季節が本格的な夏へとシフトしていく時期ですので、週末は体調を最優先に、無理せずリラックスする時間も作ってくださいね。\n\nお出かけの際も、喉が渇く前のこまめな水分補給を心がけて、素敵な土曜日をお過ごしください。😊\n\n次回更新は10:00頃です。",
  "data_summary": {
    "outdoor_temp": 24.8,
    "weather_temp": null,
    "weather": "快晴",
    "alerts_count": 0
  }
}