{
  "generated_at": "2026-01-23T08:23:38.266593+09:00",
  "advice": "現在、外気温は-0.7°C。風が穏やかなため、肌に直接感じる冷たさを示す「体感温度」も-0.8°Cと、ほぼ等しい数値になっています。\n\n今朝は0時以降に-3.2°Cを記録し、当観測所における歴代最低気温を更新する記録的な寒さとなりました。これほど冷え込んだ理由は、遮るもののない快晴の空にあります。雲が全くない夜、地表の熱が宇宙空間へと逃げていく「放射冷却」が強烈に進んだためです。通常、雲があれば大気が熱を地面へ送り返す「逆放射」という保温効果が働きますが、今朝はその機能が一切なかったことが、氷点下の冷気を生み出しました。\n\n今日は一日を通して快晴が続く予報です。お出かけの際は、厚手のコートはもちろん、マフラーや手袋で肌の露出を抑えた完全防備をおすすめします。空気が非常に乾いているため、喉の粘膜を保護するマスクも有効な防寒具になりますよ。\n\n二十四節気では「大寒」の真っ只中。一年で最も寒さが極まる時期ですが、立春まではあと11日です。春の足音は、静かに、でも確実に近づいています。今日は平日の締めくくり、金曜日ですね。お仕事帰りには、空に低くかかる繊細な三日月が、一週間の頑張りを優しく見守ってくれるはずです。暖かくして、元気に行ってらっしゃいませ！\n\n次回更新は9:00頃です。",
  "data_summary": {
    "outdoor_temp": -0.7,
    "weather_temp": -0.8,
    "weather": "快晴",
    "alerts_count": 0
  }
}