{
  "generated_at": "2026-06-16T06:46:07.457410+09:00",
  "advice": "現在、自宅軒下では0.1ミリメートルのごく弱い雨が降っており、体感温度は20.0°Cです。先週末の30°C近い暑さから一転し、今朝は少しひんやりとした空気に包まれていますね。☔️\n\nこの涼しさの理由は、北方の冷たい高気圧から湿った気流が流れ込み、日差しが遮られているためです。このように、初夏に訪れる一時的な冷え込みを「梅雨寒」と呼びます。湿度が81.0%と高いため、肌に触れる空気はしっとりとしていますが、風がほとんどないため、体感的には過ごしやすい涼しさに収まっています。\n\n今日は火曜日。お仕事や学校へと向かう時間帯ですが、お出かけのタイミングでは傘が必要になりそうです。雨はすぐに止む予報ですが、念のため折りたたみ傘をお持ちください。日中も気温はあまり上がらないため、長袖のシャツや薄手の羽織りものが1枚あると快適に過ごせますよ。体調を崩しやすい気圧と気温のバランスですので、温かい飲み物で体を内側から温めて、今日も元気にいってらっしゃいませ。💪✨\n\n次回更新は7:00頃です。",
  "data_summary": {
    "outdoor_temp": 19.7,
    "weather_temp": 17.6,
    "weather": "晴れ",
    "alerts_count": 0
  }
}