{
  "generated_at": "2026-02-20T07:33:52.216036+09:00",
  "advice": "現在の体感温度は2.3°C。吐く息が白く、指先がかじかむような冷え込みの強い金曜日の朝ですね。雲が少なく晴れているため、地表の熱が宇宙空間へ逃げていく「放射冷却」が強く働き、一段と冷え込みが厳しくなっています。\n\n今週の傾向を振り返ると、週明けには15°Cを超える春のような陽気もありましたが、そこから一気に真冬の寒さに逆戻りしました。このように数日で気温が激変すると、体温調節を司る自律神経に大きな負担がかかります。また、暖かい室内から寒い屋外へ出た際の急激な血圧変動「ヒートショック」にも注意が必要です。今日は厚手のコートにマフラーや手袋をプラスして、肌の露出を最小限に抑える「完全防備」でお出かけください。\n\n二十四節気では、雪が雨へと変わり氷が溶け出す「雨水（うすい）」の時期ですが、今日ばかりは冬の厳しさが勝っています。空気が非常に乾燥しているため、喉の粘膜を保護するマスクの着用も有効ですよ。週末まであと一歩の金曜日、温かい飲み物で心と体をほぐしながら、無理せず自分を労わってあげてくださいね。今日も一日、いってらっしゃい！\n\n次回更新は8:00頃です。",
  "data_summary": {
    "outdoor_temp": 2.4,
    "weather_temp": 0.6,
    "weather": "晴れ",
    "alerts_count": 0
  }
}