{
  "generated_at": "2026-02-07T13:08:40.948741+09:00",
  "advice": "現在は冷たい「みぞれ」が降りしきり、空気の重みを感じる土曜の昼下がりですね。外気温は3.5°Cですが、実際の肌感覚である「体感温度」は2.7°Cと、冷蔵庫の中にいるような冷え込みです。🌨️\n\n昨日は14.5°Cまで上がり春の兆しを感じましたが、今日は一転して真冬へ逆戻り。これほど急激に気温が下がるのは、北からの強い寒気が一気に南下してきたためです。現在、水が蒸発する際の冷却効果を含めた「湿球温度」が氷点下付近まで下がっているため、雨が雪へと変わりきれず「みぞれ」として降っています。\n\nせっかくの週末ですが、午後は無理な外出を控え、室内で暖かくして過ごすのが正解です。湿度が高く感じられますが、暖房を使い続けると室内の空気は急速に乾き、喉のバリア機能を弱めてしまいます。加湿器や濡れタオルを活用して、潤いを保ってくださいね。🧣\n\n今夜は22:49頃に、少し欠けた「十八夜月」が東の空から昇ってきます。夜にかけても厳しい寒さが続きますので、おやすみ前にはお風呂で芯まで体を温め、急激な温度変化で血圧が変動する「ヒートショック」に十分注意して、健やかな週末をお過ごしください。😊✨\n\n次回更新は14:00頃です。",
  "data_summary": {
    "outdoor_temp": 3.5,
    "weather_temp": 3.2,
    "weather": "薄曇り",
    "alerts_count": 0
  }
}