{
  "generated_at": "2026-05-30T17:12:38.591702+09:00",
  "advice": "今日は最高気温29.9°Cを記録し、夕方の今も体感温度は27.8°Cと、5月下旬とは思えない汗ばむ暑さが残っていますね。🌡️\n\n楽しい土曜日のディナーやお出かけからの帰り道、少しだけ服装にご注意ください。18時49分の日没を過ぎると、雲ひとつない快晴の空から地表の熱が宇宙へと逃げていく「放射冷却」が始まります。これにより夜にかけて気温が急降下し、一気に涼しくなります。日中との寒暖差で風邪をひかないよう、帰路には長袖の羽織るものが1枚あると安心ですよ。🧥\n\nまた、今夜は月齢13のほぼ満月となる美しい月が、18時7分頃に東南東の空から昇ってきます。雲が全くない澄み渡った夜空ですので、お部屋の灯りを少し落として、お月見をしながら週末の夜をゆったりと過ごすのも素敵ですね。🌕どうぞ心地よい土曜日の夜をお過ごしください。\n\n次回更新は18:00頃です。",
  "data_summary": {
    "outdoor_temp": 28.1,
    "weather_temp": 24.4,
    "weather": "快晴",
    "alerts_count": 0
  }
}