{
  "generated_at": "2026-06-25T13:55:27.677623+09:00",
  "advice": "現在の体感温度は23.8°C。夏至を過ぎたばかりの時期としては、驚くほど涼しいお昼時ですね。外ではしとしとと霧雨が降り続いており、見通せる距離を示す「視程」も約4.1kmと、白くもやがかかった景色が広がっています。\n\n今日は湿度が92.0%と非常に高いため、汗が蒸発して体温を下げる「気化熱」の効率が落ちています。そのため、体に熱や湿気がこもりやすく、気温の割には少しジメッとした感覚があるかもしれません。\n\n雨はまもなく一時的に止みますが、1時間後には再び雨脚が強まる予報です。午後に外出される方は傘をお忘れなく。また、外気温が低めな分、室内の冷房が効きすぎて冷えを強く感じることもあります。薄手の羽織るものを一枚手元に置いておくと安心ですよ。\n\n週の後半でお疲れが溜まる木曜日。温かいハーブティーでも淹れて、午後のデスクワークも心地よく進めていきましょう。応援しています！😊🌂\n\n次回更新は14:00頃です。",
  "data_summary": {
    "outdoor_temp": 21.7,
    "weather_temp": 20.9,
    "weather": "弱い霧雨",
    "alerts_count": 0
  }
}