{
  "generated_at": "2025-12-26T12:25:00.328192+09:00",
  "advice": "現在は実測気温10.1℃に対し、体感温度は7.4℃と低めです。風速2.5m/sの風が体温を奪うため、実際の数字以上に空気がピリッと冷たく感じますね。今日は朝の最低気温（7.9℃）との差が小さく、日中の気温上昇が非常に緩やかなのが特徴です。どんよりとした冬の寒さが居座るストーリーが見て取れます。\n\n一年で最も忙しい「御用納め」の金曜日、外回りや買い出しに出る際は厚手のコートが必須ですよ。また、湿度が42.0%と低く乾燥しているため、大掃除で埃を吸い込まないようマスクの着用をおすすめします。この乾燥は洗濯物の乾きを早めてくれますが、同時にお肌の水分も奪います。作業後の保湿ケアはいつもより入念に行いましょう。\n\nUV指数が3を超えており、冬の澄んだ空気を通して紫外線が意外と届いています。午後も上手に防寒と乾燥対策をして、健やかに一年を締めくくる準備を進めてくださいね。☺️🧣✨\n\n次回更新は13:00頃です。",
  "data_summary": {
    "outdoor_temp": 10.1,
    "weather_temp": 9.1,
    "weather": "快晴",
    "alerts_count": 0
  }
}