{
  "generated_at": "2025-12-27T01:30:05.138891+09:00",
  "advice": "現在の体感温度は1.0°C。雲ひとつない快晴の空の下、地表の熱が宇宙へと逃げていく「放射冷却」の影響で、空気の密度がぐっと増したような、しんしんとした冷え込みを感じます。湿度は46.0%と低く、お肌や喉の乾燥も気になる時間帯ですね。🥶\n\n今日は年末の土曜日。大掃除を計画されている方も多いかと思いますが、日中の最高気温予報は6.7°Cと、昨日の10.1°Cに比べて大幅に下がります。一気に真冬の厳しさがやってくるため、水仕事には「お湯」と「厚手のゴム手袋」が必須ですよ。🧤\n\n二十四節気の「冬至」も終盤。月齢6.6の上弦の月が沈み、朝方にかけてはさらに気温が下がっていく見込みです。お休み中の方は首元や肩口を冷やさないよう暖かくし、これから活動される方は室内外の急激な温度差によるヒートショックに十分ご注意ください。年末の忙しさで体調を崩しやすい時期ですから、無理せず「ほっこり」する時間を大切にしてくださいね。😊✨\n\n次回更新は4:00頃です。",
  "data_summary": {
    "outdoor_temp": 2.3,
    "weather_temp": 1.0,
    "weather": "快晴",
    "alerts_count": 0
  }
}