{
  "generated_at": "2026-03-28T16:38:52.020617+09:00",
  "advice": "暖かな土曜の午後、いかがお過ごしですか？現在の体感温度は17.4°Cと、薄手の長袖一枚で心地よく過ごせる「春本番」の陽気ですね。🌸\n\n今日は最高気温が実測で18.9°Cまで上がり、この一週間で最も暖かい一日となりました。空気が冷えて水蒸気が水滴に変わる境界線である「露点温度」が10.4°Cと低めに保たれているため、湿っぽさがなく、非常にさらりと快適な空気に包まれています。😊\n\nお出かけ中の方に気をつけていただきたいのが、これからの急な温度変化です。17時58分の日の入りを過ぎると、地表の熱が宇宙へと逃げていく「放射冷却」が本格的に始まります。今夜は雲が少なく、大気が熱を地面へ送り返す「逆放射」の効果が弱いため、日中の暖かさが嘘のようにヒンヤリと感じられるでしょう。\n\n夕食の買い物や帰路につく頃には、体感温度がぐっと下がります。ストールやジャケットなど、すぐに羽織れるものを用意して体温を逃さないようにしてください。今夜は輝面率75%の美しい「上弦の月」が夜空を彩ります。澄んだ空気の中、月を眺めながら心豊かな週末の夜をお過ごしくださいね。✨\n\n次回更新は17:00頃です。",
  "data_summary": {
    "outdoor_temp": 18.1,
    "weather_temp": 16.5,
    "weather": "晴れ",
    "alerts_count": 0
  }
}