{
  "generated_at": "2026-02-10T20:54:31.035888+09:00",
  "advice": "現在は6.8°C。風が穏やかなため、肌を刺すような鋭さはありませんが、足元からじわじわと冷気が忍び寄るような体感6.9°Cの夜ですね。\n\n今日は氷点下から10度超えまで気温が大きく動き、体は知らず知らずのうちに疲弊しています。火曜日の夜、週の前半を乗り切ったご自身をまずは労ってあげてください。\n\n今夜は空が厚い雲に覆われています。この雲が蓋のような役割を果たし、大気が熱を地面へ送り返す「逆放射」が働くため、晴れた夜に地表の熱が宇宙へ逃げて急激に冷え込む「放射冷却」は、今夜に限っては少し緩やかになりそうです。\n\nとはいえ、明日の朝も厳しい寒さが残ります。暖かい寝床から出た際の急激な血圧変化、いわゆる「ヒートショック」を防ぐため、今夜のうちに脱衣所やトイレを少し温めておくのが賢明な備えです。\n\n今夜は月齢22の下弦の月が昇りますが、雲に隠れてしまいそうですね。月明かりの代わりに、温かい湯船で心身をじんわり解きほぐし、明日のエネルギーを蓄えましょう。ゆっくりお休みくださいね。☺️🧣✨\n\n次回更新は21:00頃です。",
  "data_summary": {
    "outdoor_temp": 6.8,
    "weather_temp": 8.1,
    "weather": "曇り",
    "alerts_count": 0
  }
}