{
  "generated_at": "2025-12-25T15:16:58.183245+09:00",
  "advice": "クリスマスの午後、穏やかな空気に包まれていますね。現在の体感温度は11.5°C。昨日の最高気温が8.7°Cだったことを考えると、今日はいつもより3°Cほど高く、お出かけしやすい一日となりました。🎄\n\nただ、ここからの変化には注意が必要です。冬至を過ぎたばかりの今は、16時32分には日が沈んでしまいます。太陽の熱がなくなると、85%という高い湿気が「冷気の運び役」となり、肌にまとわりつくような冷たさへと変わりますよ。湿った空気は乾燥した空気よりも熱を伝えやすいため、一度体が冷えると芯まで冷え込みやすく、温まりにくいのが特徴です。\n\n夕方以降にケーキの買い出しやディナーへ向かう際は、厚手のコートにマフラーを添えて、万全の防寒対策をしてください。夜は三日月🌒が静かに見守る中、気温は一桁まで急降下します。大切な人と温かい飲み物を囲んで、ほっこりと素敵なクリスマスを過ごしてくださいね。😊🧣✨\n\n次回更新は16:00頃です。",
  "data_summary": {
    "outdoor_temp": 11.8,
    "weather_temp": 7.7,
    "weather": "曇り",
    "alerts_count": 0
  }
}