{
  "generated_at": "2026-06-19T22:34:16.632635+09:00",
  "advice": "金曜日の夜、今週も一週間本当にお疲れ様でした。お休み前のリラックスタイム、いかがお過ごしですか。😊\n\n今日の日中は手元のセンサーで31.6°Cを記録し、体に堪える真夏日となりましたね。\n夜になり、外気温は23.9°Cまで落ち着いてきましたが、湿度が84.0%と非常に高いため、肌で感じる体感温度は26.0°Cと、じっとりとした蒸し暑さが続いています。\nこの寝苦しさの原因は、空気中の豊かな水蒸気が熱を蓄える性質に加え、大気が熱を逃がさず地面へ送り返す「逆放射」の働きによって、夜間の冷え込みが妨げられているためです。\n\n今夜はエアコンの除湿機能や、26〜27°C設定の冷房を朝までつけておくのがベストです。湿度を下げるだけで体感温度が下がり、驚くほど快適に眠れますよ。寝汗による脱水を防ぐため、枕元に水分を用意しておくのも忘れずに。\n\n張り詰めた心と体を優しくほどいて、健やかな眠りにつけますように。どうぞ良い夢を見てくださいね。✨\n\n次回更新は1:00頃です。",
  "data_summary": {
    "outdoor_temp": 23.9,
    "weather_temp": 22.1,
    "weather": "薄曇り",
    "alerts_count": 0
  }
}