{
  "generated_at": "2026-05-19T22:56:26.975838+09:00",
  "advice": "現在の体感温度は20.8°C。湿度が83%と高く風も穏やかなため、肌にまとわりつくような、どこか「ぬるい」感覚を抱く夜ですね。今夜は空に薄雲が広がっているため、地面から逃げようとする熱を雲が吸収・反射して地上へ送り返す「逆放射」が働いています。おかげで春の夜特有の急激な冷え込みは抑えられ、明朝にかけても過ごしやすい気温が保たれるでしょう。\n\nしかし、明日は一転して、日中の最高気温が26°Cを超える「夏日」となる予報です。今日までの体感差が大きく、体がまだ暑さに慣れていないため、熱中症の一歩手前のような「暑熱順化」が追いつかない不調を感じやすいタイミングです。明日の外出には、脱ぎ着しやすい薄手の羽織ものを選び、意識的に水分を摂る準備をしておくと安心ですよ。\n\n三日月は先ほど西の空に沈み、夜は深まっています。湿気が多く少し寝苦しく感じるかもしれませんが、エアコンの除湿機能を活用して、最適な睡眠環境を整えてくださいね。火曜日の疲れをしっかりリセットして、明日もあなたらしく過ごせますように。🌸✨\n\n次回更新は1:00頃です。",
  "data_summary": {
    "outdoor_temp": null,
    "weather_temp": 19.6,
    "weather": "薄曇り",
    "alerts_count": 0
  }
}