{
  "generated_at": "2025-12-28T14:25:24.768439+09:00",
  "advice": "今朝の最低気温は-1.1°C。これは当観測所の記録開始以来、歴代最低記録に並ぶ歴史的な冷え込みでした。厳しい寒さで始まった日曜日ですが、午後の現在は10.5°Cまで上がり、昨日の最高気温を4度以上も上回っています。快晴の空から届く「短波放射（太陽からの光エネルギー）」が、冷え切った地表を力強く温めてくれていますね。☀️\n\n現在の体感温度は9.4°C。日差しの下では数字以上の温もりを感じますが、湿度が45%と低く空気が澄んでいるため、熱を保持する力が弱いのが冬の空の特徴です。日没の16時34分を境に、今度は地表の熱が赤外線として宇宙へと逃げていく「放射冷却」が急激に強まります。夕方以降は、体感温度が再び5度を下回る「氷点下へのカウントダウン」が始まると心得てください。🥶\n\n大掃除の窓拭きや買い出しなど、外での作業はあと1時間ほどが勝負です。日が傾く前に早めに切り上げ、夜は上弦の月を眺めながら温かい飲み物で冷えた体を労わってくださいね。☺️🧣\n\n次回更新は15:00頃です。",
  "data_summary": {
    "outdoor_temp": 10.5,
    "weather_temp": 9.5,
    "weather": "快晴",
    "alerts_count": 0
  }
}