{
  "type": "monthly",
  "period": {
    "year": 2025,
    "month": 7,
    "start_date": "2025-07-01",
    "end_date": "2025-07-31",
    "label": "2025年7月"
  },
  "generated_at": "2026-03-02T11:34:11.147688+09:00",
  "sections": {
    "summary": {
      "title": "月間サマリー",
      "ai_comment": "",
      "highlights": [
        "月平均 29.5℃",
        "最高 36.7℃",
        "前月比 +3.9℃",
        "前年比 -0.1℃"
      ]
    },
    "statistics": {
      "title": "月間統計",
      "days": 31,
      "avg_temp": 29.5,
      "avg_temp_stdev": 2.1,
      "max_temp": 36.7,
      "max_temp_date": "2025/07/24",
      "avg_high": 34.0,
      "min_temp": 21.1,
      "min_temp_date": "2025/07/12",
      "avg_low": 26.1,
      "avg_daily_range": 7.9,
      "prev_month_diff": 3.9,
      "prev_year_diff": -0.1
    },
    "daily_data": [
      {
        "date": "2025/07/01",
        "weekday": "火",
        "high": 34.5,
        "low": 26.1,
        "avg": 29.4,
        "range": 8.4
      },
      {
        "date": "2025/07/02",
        "weekday": "水",
        "high": 33.5,
        "low": 26.3,
        "avg": 29.2,
        "range": 7.2
      },
      {
        "date": "2025/07/03",
        "weekday": "木",
        "high": 34.6,
        "low": 26.6,
        "avg": 30.1,
        "range": 8.0
      },
      {
        "date": "2025/07/04",
        "weekday": "金",
        "high": 34.7,
        "low": 26.5,
        "avg": 29.8,
        "range": 8.2
      },
      {
        "date": "2025/07/05",
        "weekday": "土",
        "high": 34.9,
        "low": 27.0,
        "avg": 30.2,
        "range": 7.9
      },
      {
        "date": "2025/07/06",
        "weekday": "日",
        "high": 35.8,
        "low": 26.9,
        "avg": 30.7,
        "range": 8.9
      },
      {
        "date": "2025/07/07",
        "weekday": "月",
        "high": 36.2,
        "low": 27.9,
        "avg": 31.4,
        "range": 8.3
      },
      {
        "date": "2025/07/08",
        "weekday": "火",
        "high": 36.4,
        "low": 27.8,
        "avg": 31.7,
        "range": 8.6
      },
      {
        "date": "2025/07/09",
        "weekday": "水",
        "high": 36.0,
        "low": 28.2,
        "avg": 31.5,
        "range": 7.8
      },
      {
        "date": "2025/07/10",
        "weekday": "木",
        "high": 36.5,
        "low": 22.8,
        "avg": 29.0,
        "range": 13.7
      },
      {
        "date": "2025/07/11",
        "weekday": "金",
        "high": 25.3,
        "low": 21.9,
        "avg": 23.5,
        "range": 3.4
      },
      {
        "date": "2025/07/12",
        "weekday": "土",
        "high": 27.3,
        "low": 21.1,
        "avg": 23.9,
        "range": 6.2
      },
      {
        "date": "2025/07/13",
        "weekday": "日",
        "high": 33.2,
        "low": 22.5,
        "avg": 27.2,
        "range": 10.7
      },
      {
        "date": "2025/07/14",
        "weekday": "月",
        "high": 30.7,
        "low": 24.6,
        "avg": 27.1,
        "range": 6.1
      },
      {
        "date": "2025/07/15",
        "weekday": "火",
        "high": 30.2,
        "low": 25.6,
        "avg": 27.5,
        "range": 4.6
      },
      {
        "date": "2025/07/16",
        "weekday": "水",
        "high": 29.6,
        "low": 26.2,
        "avg": 27.4,
        "range": 3.4
      },
      {
        "date": "2025/07/17",
        "weekday": "木",
        "high": 32.3,
        "low": 25.8,
        "avg": 28.5,
        "range": 6.5
      },
      {
        "date": "2025/07/18",
        "weekday": "金",
        "high": 33.4,
        "low": 25.7,
        "avg": 29.0,
        "range": 7.7
      },
      {
        "date": "2025/07/19",
        "weekday": "土",
        "high": 35.3,
        "low": 25.8,
        "avg": 29.7,
        "range": 9.5
      },
      {
        "date": "2025/07/20",
        "weekday": "日",
        "high": 34.6,
        "low": 26.6,
        "avg": 30.3,
        "range": 8.0
      },
      {
        "date": "2025/07/21",
        "weekday": "月",
        "high": 35.9,
        "low": 27.0,
        "avg": 30.9,
        "range": 8.9
      },
      {
        "date": "2025/07/22",
        "weekday": "火",
        "high": 35.4,
        "low": 27.3,
        "avg": 30.6,
        "range": 8.1
      },
      {
        "date": "2025/07/23",
        "weekday": "水",
        "high": 35.5,
        "low": 27.3,
        "avg": 30.7,
        "range": 8.2
      },
      {
        "date": "2025/07/24",
        "weekday": "木",
        "high": 36.7,
        "low": 27.3,
        "avg": 31.1,
        "range": 9.4
      },
      {
        "date": "2025/07/25",
        "weekday": "金",
        "high": 36.0,
        "low": 27.8,
        "avg": 31.2,
        "range": 8.2
      },
      {
        "date": "2025/07/26",
        "weekday": "土",
        "high": 36.0,
        "low": 27.9,
        "avg": 31.3,
        "range": 8.1
      },
      {
        "date": "2025/07/27",
        "weekday": "日",
        "high": 35.2,
        "low": 27.9,
        "avg": 30.7,
        "range": 7.3
      },
      {
        "date": "2025/07/28",
        "weekday": "月",
        "high": 36.7,
        "low": 27.3,
        "avg": 31.4,
        "range": 9.4
      },
      {
        "date": "2025/07/29",
        "weekday": "火",
        "high": 36.5,
        "low": 27.3,
        "avg": 31.2,
        "range": 9.2
      },
      {
        "date": "2025/07/30",
        "weekday": "水",
        "high": 33.7,
        "low": 26.0,
        "avg": 29.3,
        "range": 7.7
      },
      {
        "date": "2025/07/31",
        "weekday": "木",
        "high": 32.1,
        "low": 24.8,
        "avg": 27.9,
        "range": 7.3
      }
    ],
    "weekly_breakdown": [
      {
        "start_date": "2025-07-01",
        "end_date": "2025-07-07",
        "label": "7/1〜7/7",
        "days": 7,
        "avg_temp": 30.1,
        "avg_temp_stdev": 0.8,
        "max_temp": 36.2,
        "max_temp_date": "2025/07/07",
        "avg_high": 34.9,
        "min_temp": 26.1,
        "min_temp_date": "2025/07/01",
        "avg_low": 26.8,
        "avg_daily_range": 8.1
      },
      {
        "start_date": "2025-07-08",
        "end_date": "2025-07-14",
        "label": "7/8〜7/14",
        "days": 7,
        "avg_temp": 27.7,
        "avg_temp_stdev": 3.3,
        "max_temp": 36.5,
        "max_temp_date": "2025/07/10",
        "avg_high": 32.2,
        "min_temp": 21.1,
        "min_temp_date": "2025/07/12",
        "avg_low": 24.1,
        "avg_daily_range": 8.1
      },
      {
        "start_date": "2025-07-15",
        "end_date": "2025-07-21",
        "label": "7/15〜7/21",
        "days": 7,
        "avg_temp": 29.0,
        "avg_temp_stdev": 1.3,
        "max_temp": 35.9,
        "max_temp_date": "2025/07/21",
        "avg_high": 33.0,
        "min_temp": 25.6,
        "min_temp_date": "2025/07/15",
        "avg_low": 26.1,
        "avg_daily_range": 6.9
      },
      {
        "start_date": "2025-07-22",
        "end_date": "2025-07-28",
        "label": "7/22〜7/28",
        "days": 7,
        "avg_temp": 31.0,
        "avg_temp_stdev": 0.3,
        "max_temp": 36.7,
        "max_temp_date": "2025/07/24",
        "avg_high": 35.9,
        "min_temp": 27.3,
        "min_temp_date": "2025/07/22",
        "avg_low": 27.5,
        "avg_daily_range": 8.4
      },
      {
        "start_date": "2025-07-29",
        "end_date": "2025-07-31",
        "label": "7/29〜7/31",
        "days": 3,
        "avg_temp": 29.5,
        "avg_temp_stdev": 1.7,
        "max_temp": 36.5,
        "max_temp_date": "2025/07/29",
        "avg_high": 34.1,
        "min_temp": 24.8,
        "min_temp_date": "2025/07/31",
        "avg_low": 26.0,
        "avg_daily_range": 8.1
      }
    ],
    "comparison": {
      "title": "前年同月比較",
      "prev_year_month": {
        "year": 2024,
        "month": 7,
        "days": 31,
        "avg_temp": 29.6,
        "avg_temp_stdev": 2.4,
        "max_temp": 39.1,
        "max_temp_date": "2024/07/29",
        "avg_high": 34.6,
        "min_temp": 22.5,
        "min_temp_date": "2024/07/17",
        "avg_low": 25.9,
        "avg_daily_range": 8.8
      },
      "avg_temp_diff": -0.1,
      "max_temp_diff": -2.4,
      "min_temp_diff": -1.4,
      "avg_daily_range_diff": -0.9,
      "ai_comment": ""
    },
    "prev_month": {
      "title": "前月比較",
      "prev_month_stats": {
        "days": 30,
        "avg_temp": 25.6,
        "avg_temp_stdev": 3.3,
        "max_temp": 36.3,
        "max_temp_date": "2025/06/17",
        "avg_high": 30.0,
        "min_temp": 16.0,
        "min_temp_date": "2025/06/01",
        "avg_low": 22.3,
        "avg_daily_range": 7.7
      },
      "avg_temp_diff": 3.9,
      "max_temp_diff": 0.4,
      "min_temp_diff": 5.1,
      "avg_daily_range_diff": 0.2,
      "ai_comment": ""
    },
    "baseline": {
      "title": "2年平均との比較",
      "baseline_avg": 29.6,
      "current_deviation": -0.1,
      "years_count": 1,
      "ai_comment": ""
    },
    "events": {
      "title": "特筆イベント",
      "items": [
        {
          "date": "2025/07/06〜2025/07/10",
          "type": "extreme_heat",
          "description": "猛暑日5日連続（最高気温35.8℃〜最高気温36.5℃）"
        },
        {
          "date": "2025/07/11",
          "type": "rapid_change",
          "description": "平均気温が前日比-5.5℃の急低下"
        },
        {
          "date": "2025/07/19",
          "type": "extreme_heat",
          "description": "猛暑日: 最高気温35.3℃"
        },
        {
          "date": "2025/07/21〜2025/07/29",
          "type": "extreme_heat",
          "description": "猛暑日9日連続（最高気温35.9℃〜最高気温36.5℃）"
        }
      ],
      "ai_comment": ""
    },
    "season": {
      "title": "季節の進み具合",
      "milestones": [
        {
          "label": "初めて10℃超え",
          "2024": "2024/03/12",
          "2025": "2025/01/01",
          "2026": "2026/01/05"
        },
        {
          "label": "初めて20℃超え",
          "2024": "2024/03/16",
          "2025": "2025/03/02",
          "2026": "2026/02/23"
        },
        {
          "label": "初めて25℃超え",
          "2024": "2024/03/31",
          "2025": "2025/03/28",
          "2026": null
        },
        {
          "label": "初めて30℃超え",
          "2024": "2024/06/11",
          "2025": "2025/05/20",
          "2026": null
        },
        {
          "label": "初めて35℃超え",
          "2024": "2024/07/04",
          "2025": "2025/06/17",
          "2026": null
        },
        {
          "label": "初めて氷点下",
          "2024": "2024/12/29",
          "2025": "2025/01/05",
          "2026": "2026/01/08"
        }
      ],
      "ai_comment": ""
    },
    "heatmap": {
      "title": "気温ヒートマップ",
      "data": {
        "2024": {
          "3": {
            "avg": 10.9,
            "high": 26.6,
            "low": 2.8
          },
          "4": {
            "avg": 17.5,
            "high": 28.9,
            "low": 7.1
          },
          "5": {
            "avg": 20.6,
            "high": 29.6,
            "low": 9.6
          },
          "6": {
            "avg": 24.0,
            "high": 34.5,
            "low": 16.1
          },
          "7": {
            "avg": 29.6,
            "high": 39.1,
            "low": 22.5
          },
          "8": {
            "avg": 30.2,
            "high": 38.1,
            "low": 24.2
          },
          "9": {
            "avg": 27.3,
            "high": 35.6,
            "low": 17.8
          },
          "10": {
            "avg": 20.8,
            "high": 31.6,
            "low": 10.7
          },
          "11": {
            "avg": 13.8,
            "high": 22.9,
            "low": 4.8
          },
          "12": {
            "avg": 7.7,
            "high": 17.2,
            "low": -0.3
          }
        },
        "2025": {
          "1": {
            "avg": 6.1,
            "high": 13.5,
            "low": -1.1
          },
          "2": {
            "avg": 6.3,
            "high": 16.3,
            "low": -0.8
          },
          "3": {
            "avg": 10.7,
            "high": 25.1,
            "low": 0.8
          },
          "4": {
            "avg": 15.9,
            "high": 27.6,
            "low": 4.2
          },
          "5": {
            "avg": 19.6,
            "high": 30.0,
            "low": 12.7
          },
          "6": {
            "avg": 25.6,
            "high": 36.3,
            "low": 16.0
          },
          "7": {
            "avg": 29.5,
            "high": 36.7,
            "low": 21.1
          },
          "8": {
            "avg": 30.3,
            "high": 37.6,
            "low": 24.3
          },
          "9": {
            "avg": 27.1,
            "high": 36.2,
            "low": 18.0
          },
          "10": {
            "avg": 18.8,
            "high": 29.2,
            "low": 9.9
          },
          "11": {
            "avg": 12.7,
            "high": 21.3,
            "low": 4.7
          },
          "12": {
            "avg": 7.8,
            "high": 18.9,
            "low": -1.1
          }
        },
        "2026": {
          "1": {
            "avg": 5.5,
            "high": 16.3,
            "low": -3.2
          },
          "2": {
            "avg": 7.6,
            "high": 21.9,
            "low": -2.2
          },
          "3": {
            "avg": 11.4,
            "high": 17.3,
            "low": 8.3
          }
        }
      }
    }
  },
  "chart_data": {
    "daily_temps": {
      "labels": [
        "1日",
        "2日",
        "3日",
        "4日",
        "5日",
        "6日",
        "7日",
        "8日",
        "9日",
        "10日",
        "11日",
        "12日",
        "13日",
        "14日",
        "15日",
        "16日",
        "17日",
        "18日",
        "19日",
        "20日",
        "21日",
        "22日",
        "23日",
        "24日",
        "25日",
        "26日",
        "27日",
        "28日",
        "29日",
        "30日",
        "31日"
      ],
      "highs": [
        34.5,
        33.5,
        34.6,
        34.7,
        34.9,
        35.8,
        36.2,
        36.4,
        36.0,
        36.5,
        25.3,
        27.3,
        33.2,
        30.7,
        30.2,
        29.6,
        32.3,
        33.4,
        35.3,
        34.6,
        35.9,
        35.4,
        35.5,
        36.7,
        36.0,
        36.0,
        35.2,
        36.7,
        36.5,
        33.7,
        32.1
      ],
      "lows": [
        26.1,
        26.3,
        26.6,
        26.5,
        27.0,
        26.9,
        27.9,
        27.8,
        28.2,
        22.8,
        21.9,
        21.1,
        22.5,
        24.6,
        25.6,
        26.2,
        25.8,
        25.7,
        25.8,
        26.6,
        27.0,
        27.3,
        27.3,
        27.3,
        27.8,
        27.9,
        27.9,
        27.3,
        27.3,
        26.0,
        24.8
      ],
      "avgs": [
        29.4,
        29.2,
        30.1,
        29.8,
        30.2,
        30.7,
        31.4,
        31.7,
        31.5,
        29.0,
        23.5,
        23.9,
        27.2,
        27.1,
        27.5,
        27.4,
        28.5,
        29.0,
        29.7,
        30.3,
        30.9,
        30.6,
        30.7,
        31.1,
        31.2,
        31.3,
        30.7,
        31.4,
        31.2,
        29.3,
        27.9
      ]
    },
    "prev_year_comparison": {
      "labels": [
        "1日",
        "2日",
        "3日",
        "4日",
        "5日",
        "6日",
        "7日",
        "8日",
        "9日",
        "10日",
        "11日",
        "12日",
        "13日",
        "14日",
        "15日",
        "16日",
        "17日",
        "18日",
        "19日",
        "20日",
        "21日",
        "22日",
        "23日",
        "24日",
        "25日",
        "26日",
        "27日",
        "28日",
        "29日",
        "30日",
        "31日"
      ],
      "this_year": [
        29.4,
        29.2,
        30.1,
        29.8,
        30.2,
        30.7,
        31.4,
        31.7,
        31.5,
        29.0,
        23.5,
        23.9,
        27.2,
        27.1,
        27.5,
        27.4,
        28.5,
        29.0,
        29.7,
        30.3,
        30.9,
        30.6,
        30.7,
        31.1,
        31.2,
        31.3,
        30.7,
        31.4,
        31.2,
        29.3,
        27.9
      ],
      "last_year": [
        27.2,
        28.1,
        28.2,
        30.4,
        30.8,
        29.6,
        30.3,
        32.0,
        31.2,
        30.8,
        28.9,
        25.3,
        27.3,
        25.7,
        24.6,
        24.2,
        26.5,
        29.2,
        30.6,
        31.9,
        30.3,
        30.8,
        30.6,
        31.1,
        31.2,
        30.8,
        31.3,
        32.8,
        33.7,
        31.9,
        30.7
      ],
      "this_year_high": [
        34.5,
        33.5,
        34.6,
        34.7,
        34.9,
        35.8,
        36.2,
        36.4,
        36.0,
        36.5,
        25.3,
        27.3,
        33.2,
        30.7,
        30.2,
        29.6,
        32.3,
        33.4,
        35.3,
        34.6,
        35.9,
        35.4,
        35.5,
        36.7,
        36.0,
        36.0,
        35.2,
        36.7,
        36.5,
        33.7,
        32.1
      ],
      "last_year_high": [
        30.1,
        32.2,
        34.0,
        35.8,
        36.4,
        35.9,
        35.9,
        37.7,
        37.2,
        35.2,
        31.4,
        27.1,
        32.7,
        29.0,
        27.9,
        27.0,
        31.5,
        35.3,
        34.8,
        38.9,
        36.2,
        38.2,
        36.0,
        37.5,
        36.3,
        36.3,
        37.8,
        38.1,
        39.1,
        37.3,
        35.2
      ],
      "this_year_low": [
        26.1,
        26.3,
        26.6,
        26.5,
        27.0,
        26.9,
        27.9,
        27.8,
        28.2,
        22.8,
        21.9,
        21.1,
        22.5,
        24.6,
        25.6,
        26.2,
        25.8,
        25.7,
        25.8,
        26.6,
        27.0,
        27.3,
        27.3,
        27.3,
        27.8,
        27.9,
        27.9,
        27.3,
        27.3,
        26.0,
        24.8
      ],
      "last_year_low": [
        25.4,
        25.0,
        23.9,
        26.0,
        26.4,
        26.4,
        25.5,
        27.5,
        27.3,
        27.6,
        26.6,
        22.7,
        23.0,
        23.8,
        23.3,
        22.7,
        22.5,
        24.4,
        27.5,
        26.8,
        25.8,
        26.1,
        25.7,
        26.6,
        27.4,
        26.6,
        27.0,
        27.5,
        30.3,
        27.5,
        27.4
      ]
    },
    "deviation": {
      "labels": [
        "7/1(火)",
        "7/2(水)",
        "7/3(木)",
        "7/4(金)",
        "7/5(土)",
        "7/6(日)",
        "7/7(月)",
        "7/8(火)",
        "7/9(水)",
        "7/10(木)",
        "7/11(金)",
        "7/12(土)",
        "7/13(日)",
        "7/14(月)",
        "7/15(火)",
        "7/16(水)",
        "7/17(木)",
        "7/18(金)",
        "7/19(土)",
        "7/20(日)",
        "7/21(月)",
        "7/22(火)",
        "7/23(水)",
        "7/24(木)",
        "7/25(金)",
        "7/26(土)",
        "7/27(日)",
        "7/28(月)",
        "7/29(火)",
        "7/30(水)",
        "7/31(木)"
      ],
      "deviations": [
        -0.2,
        -0.4,
        0.5,
        0.2,
        0.6,
        1.1,
        1.8,
        2.1,
        1.9,
        -0.6,
        -6.1,
        -5.7,
        -2.4,
        -2.5,
        -2.1,
        -2.2,
        -1.1,
        -0.6,
        0.1,
        0.7,
        1.3,
        1.0,
        1.1,
        1.5,
        1.6,
        1.7,
        1.1,
        1.8,
        1.6,
        -0.3,
        -1.7
      ],
      "baseline_avg": 29.6
    },
    "weekly_trend_in_month": {
      "labels": [
        "7/1〜7/7",
        "7/8〜7/14",
        "7/15〜7/21",
        "7/22〜7/28",
        "7/29〜7/31"
      ],
      "avgs": [
        30.1,
        27.7,
        29.0,
        31.0,
        29.5
      ],
      "highs": [
        34.9,
        32.2,
        33.0,
        35.9,
        34.1
      ],
      "lows": [
        26.8,
        24.1,
        26.1,
        27.5,
        26.0
      ]
    }
  }
}